ai_parade/__init__.py
ai_parade/_compat.py
ai_parade/custom_definitions.py
ai_parade/datasets.py
ai_parade/logging.py
ai_parade/toolkit.py
ai_parade/_cli/ai_parade/main.py
ai_parade/_cli/ai_parade_puppet/communication.py
ai_parade/_cli/ai_parade_puppet/main.py
ai_parade/_toolkit/__init__.py
ai_parade/_toolkit/capture_outputs.py
ai_parade/_toolkit/constants.py
ai_parade/_toolkit/get_weights.py
ai_parade/_toolkit/logging.py
ai_parade/_toolkit/structural_mapping.py
ai_parade/_toolkit/sys_path_checkpoint.py
ai_parade/_toolkit/verify.py
ai_parade/_toolkit/converters/README.md
ai_parade/_toolkit/converters/__init__.py
ai_parade/_toolkit/converters/_onnx_simplify.py
ai_parade/_toolkit/converters/_pytorch_base.py
ai_parade/_toolkit/converters/ai_edge_torch.py
ai_parade/_toolkit/converters/converter.py
ai_parade/_toolkit/converters/executorch.py
ai_parade/_toolkit/converters/liteRT.py
ai_parade/_toolkit/converters/nobuco.py
ai_parade/_toolkit/converters/onnx.py
ai_parade/_toolkit/converters/onnx2tf.py
ai_parade/_toolkit/converters/onnx_tf.py
ai_parade/_toolkit/converters/pnnx.py
ai_parade/_toolkit/converters/pytorch.py
ai_parade/_toolkit/converters/select.py
ai_parade/_toolkit/data/ImageInput.py
ai_parade/_toolkit/data/__init__.py
ai_parade/_toolkit/data/output.py
ai_parade/_toolkit/data/postprocessing.py
ai_parade/_toolkit/data/preprocessing.py
ai_parade/_toolkit/data/datasets/Dataset.py
ai_parade/_toolkit/data/datasets/FileDataset.py
ai_parade/_toolkit/data/datasets/IterableDataset.py
ai_parade/_toolkit/data/datasets/Random.py
ai_parade/_toolkit/data/datasets/_PascalVOC.py
ai_parade/_toolkit/data/datasets/__init__.py
ai_parade/_toolkit/data/datasets/coco.py
ai_parade/_toolkit/data/datasets/load.py
ai_parade/_toolkit/engine_metadata/ONNXRuntime.py
ai_parade/_toolkit/engine_metadata/__init__.py
ai_parade/_toolkit/engine_metadata/_common.py
ai_parade/_toolkit/engine_metadata/executorch.py
ai_parade/_toolkit/engine_metadata/liteRT.py
ai_parade/_toolkit/engine_metadata/ncnn.py
ai_parade-0.1.0a1.dist-info/METADATA
ai_parade-0.1.0a1.dist-info/WHEEL
ai_parade-0.1.0a1.dist-info/entry_points.txt
ai_parade-0.1.0a1.dist-info/RECORD
