Metadata-Version: 2.4
Name: ai-parade
Version: 0.1.0a1
Requires-Python: >=3.10
Requires-Dist: backports-strenum<2.0,>=1.3.1; python_version < '3.11'
Requires-Dist: micropipenv>=1.9.0
Requires-Dist: numpy>=2.0.2
Requires-Dist: opencv-python>=4.11.0.86
Requires-Dist: pydantic
Requires-Dist: tomli; python_version < '3.11'
Requires-Dist: typer>=0.15.2
Requires-Dist: uv>=0.9.0
Requires-Dist: xmltodict>=0.14.2
Provides-Extra: convert
Requires-Dist: ai-edge-torch; extra == 'convert'
Requires-Dist: executorch>=1.0; extra == 'convert'
Requires-Dist: nobuco; extra == 'convert'
Requires-Dist: onnx2tf; extra == 'convert'
Requires-Dist: onnxconverter-common; extra == 'convert'
Requires-Dist: onnxruntime; extra == 'convert'
Requires-Dist: onnxscript; extra == 'convert'
Requires-Dist: onnxslim; extra == 'convert'
Requires-Dist: pnnx; extra == 'convert'
Requires-Dist: tf2onnx; extra == 'convert'
Requires-Dist: torch>=2.9; extra == 'convert'
Provides-Extra: convert-ncnn
Requires-Dist: pnnx; extra == 'convert-ncnn'
Provides-Extra: convert-onnx
Requires-Dist: onnxconverter-common; extra == 'convert-onnx'
Requires-Dist: onnxruntime; extra == 'convert-onnx'
Requires-Dist: onnxscript; extra == 'convert-onnx'
Requires-Dist: onnxslim; extra == 'convert-onnx'
Provides-Extra: convert-pytorch
Requires-Dist: executorch>=1.0; extra == 'convert-pytorch'
Requires-Dist: torch>=2.9; extra == 'convert-pytorch'
Provides-Extra: convert-tf
Requires-Dist: ai-edge-torch; extra == 'convert-tf'
Requires-Dist: nobuco; extra == 'convert-tf'
Requires-Dist: onnx2tf; extra == 'convert-tf'
Requires-Dist: tf2onnx; extra == 'convert-tf'
Provides-Extra: inference
Requires-Dist: ncnn; extra == 'inference'
Requires-Dist: onnxruntime; extra == 'inference'
Requires-Dist: tensorflow; extra == 'inference'
Requires-Dist: torch; extra == 'inference'
Provides-Extra: inference-ncnn
Requires-Dist: ncnn; extra == 'inference-ncnn'
Provides-Extra: inference-onnx
Requires-Dist: onnxruntime; extra == 'inference-onnx'
Provides-Extra: inference-pytorch
Requires-Dist: torch; extra == 'inference-pytorch'
Provides-Extra: inference-tf
Requires-Dist: tensorflow; extra == 'inference-tf'
